nacolla/__init__.py
nacolla/flow.py
nacolla/models.py
nacolla/operations/__init__.py
nacolla/operations/merge.py
nacolla/parsing/__init__.py
nacolla/parsing/flow_file_specification.py
nacolla/parsing/implementation_map_file_specification.py
nacolla/parsing/parse_flow.py
nacolla/parsing/parse_implementation.py
nacolla/parsing/parse_implementation_map.py
nacolla/stateful_callable.py
nacolla/step.py
nacolla/utilities/__init__.py
nacolla/utilities/dispatching_utilities.py
nacolla/utilities/generics.py
nacolla/utilities/type_utilities.py
nacolla-0.1.5.dist-info/LICENSE
nacolla-0.1.5.dist-info/METADATA
nacolla-0.1.5.dist-info/WHEEL
nacolla-0.1.5.dist-info/RECORD
